urlparser/__init__.py
urlparser/urlparser.py
urlparser-0.1.1.dist-info/LICENSE
urlparser-0.1.1.dist-info/METADATA
urlparser-0.1.1.dist-info/WHEEL
urlparser-0.1.1.dist-info/entry_points.txt
urlparser-0.1.1.dist-info/top_level.txt
urlparser-0.1.1.dist-info/RECORD
