Metadata-Version: 2.1
Name: urlparser
Version: 0.1.1
Summary: UNKNOWN
Home-page: https://github.com/tedivm/urlparser
Author: Robert Hafner
Author-email: tedivm@tedivm.com
License: UNKNOWN
Download-URL: https://github.com/tedivm/urlparser/archive/v0.1.1.tar.gz
Platform: UNKNOWN
Classifier: Development Status :: 4 - Beta
Classifier: License :: OSI Approved :: MIT License
Classifier: Intended Audience :: Developers
Classifier: Intended Audience :: System Administrators
Classifier: Programming Language :: Python :: 3
Classifier: Environment :: Console
Requires-Python: >=3
Requires-Dist: click (<8.0,>=6.0)
Provides-Extra: dev
Requires-Dist: pypandoc; extra == 'dev'
Requires-Dist: twine; extra == 'dev'
Requires-Dist: wheel; extra == 'dev'
